icds/__init__.py
icds/data.py
icds/git_helpers.py
icds/llm_interface.py
icds/models.py
icds/settings.py
icodes.py
icodes-0.1.4.dist-info/LICENSE
icodes-0.1.4.dist-info/METADATA
icodes-0.1.4.dist-info/WHEEL
icodes-0.1.4.dist-info/entry_points.txt
icodes-0.1.4.dist-info/RECORD
