Metadata-Version: 2.1
Name: icodes
Version: 0.1.4
Summary: LLM-powered Git archeology tool (a.k.a. Intelligent Commit Ontology Distiller and Enhanced Search)
Home-page: https://github.com/a115/iCODES
License: CC0-1.0
Keywords: git,llm,archeology,commit,search
Author: Jordan Dimov
Author-email: jdimov@a115.co.uk
Requires-Python: >=3.11,<4.0
Classifier: License :: CC0 1.0 Universal (CC0 1.0) Public Domain Dedication
Classifier: Operating System :: OS Independent
Classifier: Programming Language :: Python :: 3
Classifier: Programming Language :: Python :: 3.11
Requires-Dist: gitpython (>=3.1.43,<4.0.0)
Requires-Dist: loguru (>=0.7.2,<0.8.0)
Requires-Dist: openai (>=1.14.3,<2.0.0)
Requires-Dist: pydantic-settings (>=2.2.1,<3.0.0)
Requires-Dist: sqlmodel (>=0.0.16,<0.0.17)
Requires-Dist: tenacity (>=8.2.3,<9.0.0)
Requires-Dist: tiktoken (>=0.6.0,<0.7.0)
Requires-Dist: typer (>=0.12.0,<0.13.0)
Project-URL: Documentation, https://github.com/a115/iCODES
Project-URL: Repository, https://github.com/a115/iCODES
